maple_cluster_statsd/__init__.py
maple_cluster_statsd/constants.py
maple_cluster_statsd/stat_reader.py
maple_cluster_statsd/stat_reporter.py
maple_cluster_statsd-2.3.4.dist-info/LICENSE
maple_cluster_statsd-2.3.4.dist-info/METADATA
maple_cluster_statsd-2.3.4.dist-info/WHEEL
maple_cluster_statsd-2.3.4.dist-info/top_level.txt
maple_cluster_statsd-2.3.4.dist-info/RECORD
