Metadata-Version: 2.1
Name: maple-cluster-statsd
Version: 2.3.4
Summary: upload maple cluster stat to statsd
Home-page: https://github.com/dantezhu/maple_cluster_statsd
Author: dantezhu
Author-email: dantezhu <zny2008@gmail.com>
License: MIT
Project-URL: Homepage, https://github.com/dantezhu/maple_cluster_statsd
Platform: any
License-File: LICENSE
Requires-Dist: statsd
